README.md
setup.py
TreepyParser/__init__.py
TreepyParser/dom_tree.py
TreepyParser/parser.py
TreepyParser.egg-info/PKG-INFO
TreepyParser.egg-info/SOURCES.txt
TreepyParser.egg-info/dependency_links.txt
TreepyParser.egg-info/top_level.txt