Metadata-Version: 2.1
Name: TreepyParser
Version: 1.1.0
Summary: A python library that parses html into a tree structure
Home-page: https://github.com/Fab-cio612/TreepyParser
Author: Fabio Cioni
Author-email: fab.cioni6@gmail.com
License: MIT
Keywords: html,web,parser
Platform: UNKNOWN
Classifier: Programming Language :: Python :: 3
Classifier: License :: OSI Approved :: MIT License
Classifier: Operating System :: OS Independent
Requires-Python: >=3.6
